ublox_lara_r2-0.0.1.dist-info/top_level.txt
ublox_lara_r2-0.0.1.dist-info/DESCRIPTION.rst
ublox_lara_r2-0.0.1.dist-info/WHEEL
ublox_lara_r2-0.0.1.dist-info/METADATA
ublox_lara_r2-0.0.1.dist-info/RECORD
ublox_lara_r2-0.0.1.dist-info/metadata.json
ublox_lara_r2-0.0.1.data/scripts/rpirtscts
ublox_lara_r2/__init__.py
ublox_lara_r2/ublox_lara_r2.py
