Metadata-Version: 2.0
Name: ublox-lara-r2
Version: 0.0.1
Summary: LTE Pi Hat driver using celluar module ublox lara r2 LTE Cat.1.
Home-page: https://www.github.com/Seeed-Studio/ublox_lara_r2_pi_hat
Author: Lambor
Author-email: lanselambor@gmail.com
License: MIT
Keywords: ublox lara r2,ublox,R211,R204,LTE,Cat.1
Platform: UNKNOWN
Classifier: Programming Language :: Python :: 2
Classifier: Programming Language :: Python :: 2.7
Classifier: License :: OSI Approved :: MIT License
Classifier: Operating System :: POSIX :: Linux
